sigma/backends/test/__init__.py
sigma/backends/test/backend.py
sigma/collection.py
sigma/conditions.py
sigma/conversion/__init__.py
sigma/conversion/base.py
sigma/conversion/deferred.py
sigma/conversion/state.py
sigma/correlations.py
sigma/data/mitre_attack.py
sigma/data/mitre_d3fend.py
sigma/exceptions.py
sigma/filters.py
sigma/modifiers.py
sigma/pipelines/base.py
sigma/pipelines/common.py
sigma/pipelines/test/__init__.py
sigma/pipelines/test/pipeline.py
sigma/plugins.py
sigma/processing/__init__.py
sigma/processing/condition_expressions.py
sigma/processing/conditions/__init__.py
sigma/processing/conditions/base.py
sigma/processing/conditions/fields.py
sigma/processing/conditions/rule.py
sigma/processing/conditions/state.py
sigma/processing/conditions/values.py
sigma/processing/finalization.py
sigma/processing/pipeline.py
sigma/processing/postprocessing.py
sigma/processing/resolver.py
sigma/processing/templates.py
sigma/processing/tracking.py
sigma/processing/transformations/__init__.py
sigma/processing/transformations/base.py
sigma/processing/transformations/condition.py
sigma/processing/transformations/detection_item.py
sigma/processing/transformations/failure.py
sigma/processing/transformations/fields.py
sigma/processing/transformations/meta.py
sigma/processing/transformations/placeholder.py
sigma/processing/transformations/rule.py
sigma/processing/transformations/state.py
sigma/processing/transformations/values.py
sigma/py.typed
sigma/rule/__init__.py
sigma/rule/attributes.py
sigma/rule/base.py
sigma/rule/detection.py
sigma/rule/logsource.py
sigma/rule/rule.py
sigma/types.py
sigma/validation.py
sigma/validators/base.py
sigma/validators/core/__init__.py
sigma/validators/core/condition.py
sigma/validators/core/logsources.py
sigma/validators/core/metadata.py
sigma/validators/core/modifiers.py
sigma/validators/core/tags.py
sigma/validators/core/values.py
pysigma-1.1.0.dist-info/METADATA
pysigma-1.1.0.dist-info/WHEEL
pysigma-1.1.0.dist-info/licenses/LICENSE
pysigma-1.1.0.dist-info/RECORD
