Metadata-Version: 2.4
Name: pySigma
Version: 1.1.0
Summary: Sigma rule processing and conversion tools
License-Expression: LGPL-2.1-only
License-File: LICENSE
Author: Thomas Patzke
Author-email: thomas@patzke.org
Requires-Python: >=3.10,<4.0
Classifier: Development Status :: 4 - Beta
Classifier: Intended Audience :: Developers
Classifier: License :: OSI Approved :: GNU Lesser General Public License v2 (LGPLv2)
Classifier: Programming Language :: Python :: 3.10
Classifier: Programming Language :: Python :: 3.11
Classifier: Programming Language :: Python :: 3.12
Classifier: Programming Language :: Python :: 3.13
Classifier: Programming Language :: Python :: 3.14
Classifier: Topic :: Security
Requires-Dist: diskcache (>=5.6.3,<6.0.0)
Requires-Dist: diskcache-stubs (>=5.6.3.6.20240818,<6.0.0.0.0)
Requires-Dist: jinja2 (>=3.1.6,<4.0.0)
Requires-Dist: packaging (>=25.0,<26.0)
Requires-Dist: pyparsing (>=3.2.5,<4.0.0)
Requires-Dist: pyyaml (>=6.0.3,<7.0.0)
Requires-Dist: requests (>=2.32.5,<3.0.0)
Requires-Dist: types-pyyaml (>=6.0.12.20250915,<7.0.0.0)
Requires-Dist: typing-extensions (>=4.15.0,<5.0.0)
Project-URL: Repository, https://github.com/SigmaHQ/pySigma
